coderunner/__init__.py
coderunner/coderunner.py
coderunner-1.0.dist-info/LICENSE
coderunner-1.0.dist-info/METADATA
coderunner-1.0.dist-info/WHEEL
coderunner-1.0.dist-info/top_level.txt
coderunner-1.0.dist-info/RECORD
