Metadata-Version: 2.1
Name: coderunner
Version: 1.0
Summary: A judge for your programs, run and test your programs using python
Home-page: https://codeclassroom.github.io/CodeRunner/
Author: Bhupesh Varshney
Author-email: varshneybhupesh@gmail.com
License: MIT
Project-URL: Documentation, https://coderunner.readthedocs.io/en/latest/
Project-URL: Source Code, https://github.com/codeclassroom/CodeRunner
Project-URL: Funding, https://www.patreon.com/bePatron?u=18082750
Project-URL: Say Thanks!, https://github.com/codeclassroom/CodeRunner/issues/new?assignees=&labels=&template=---say-thank-you.md&title=
Project-URL: Tracker, https://github.com/codeclassroom/CodeRunner/issues
Keywords: judge0 coderunner judge0api codeclassroom
Platform: UNKNOWN
Classifier: Programming Language :: Python :: 3
Classifier: Programming Language :: Python :: 3.6
Classifier: Programming Language :: Python :: 3.7
Classifier: Programming Language :: Python :: 3.8
Classifier: Programming Language :: Python :: 3 :: Only
Classifier: License :: OSI Approved :: MIT License
Classifier: Topic :: Education
Classifier: Topic :: Education
Classifier: Topic :: Software Development
Classifier: Topic :: Software Development :: Libraries
Classifier: Topic :: Software Development :: Libraries :: Python Modules
Classifier: Operating System :: OS Independent
Requires-Python: >=3.6
